ormodel/__init__.py
ormodel/base.py
ormodel/database.py
ormodel/exceptions.py
ormodel/manager.py
ormodel/py.typed
ormodel/types.py
ormodel-0.3.1.dist-info/METADATA
ormodel-0.3.1.dist-info/WHEEL
ormodel-0.3.1.dist-info/licenses/LICENSE
ormodel-0.3.1.dist-info/RECORD
