Metadata-Version: 2.4
Name: ormodel
Version: 0.3.1
Summary: An async ORM using SQLModel with a Django-like query syntax.
Project-URL: Homepage, https://github.com/PolarBearEs/ORModel
Project-URL: Repository, https://github.com/PolarBearEs/ORModel
Author-email: PolarBearEs <contact@polarbear.es>
License: MIT License
License-File: LICENSE
Classifier: Framework :: AsyncIO
Classifier: License :: OSI Approved :: MIT License
Classifier: Operating System :: OS Independent
Classifier: Programming Language :: Python :: 3
Classifier: Programming Language :: Python :: 3.11
Classifier: Programming Language :: Python :: 3.12
Classifier: Programming Language :: Python :: 3.13
Classifier: Topic :: Database
Requires-Python: >=3.11
Requires-Dist: sqlmodel>=0.0.25
Provides-Extra: dev
Requires-Dist: aiosqlite>=0.21.0; extra == 'dev'
Requires-Dist: fastapi>=0.118.2; extra == 'dev'
Requires-Dist: httpx==0.28.1; extra == 'dev'
Requires-Dist: mypy>=1.18.2; extra == 'dev'
Requires-Dist: orjson==3.11.3; extra == 'dev'
Requires-Dist: pydantic-settings==2.11.0; extra == 'dev'
Requires-Dist: pytest-asyncio>=1.2.0; extra == 'dev'
Requires-Dist: pytest-cov>=7.0.0; extra == 'dev'
Requires-Dist: pytest-env==1.1.5; extra == 'dev'
Requires-Dist: pytest>=8.4.2; extra == 'dev'
Requires-Dist: ruff>=0.14.0; extra == 'dev'
Requires-Dist: uv>=0.9.0; extra == 'dev'
Requires-Dist: uvicorn[standard]>=0.37.0; extra == 'dev'
